Workbook

Sheet Старт
A1: Как пользоваться
A2: 1. Настройки — укажите возраст, цель и ожидаемую доходность (жёлтые ячейки).
A3: 2. Операции — все доходы и расходы. Подписки записывайте в «Подписки», а не в «Операции».
A4: 3. Подписки — регулярные платежи. Учитываются каждый месяц автоматически.
A5: 4. Долги — кредиты, займы, лизинг, рассрочки, долги другим и вам. Остаток считается сам.
A6: 5. Платежи — каждый платёж по долгу (отдаёте или получаете). Остаток долга уменьшается.
A7: 6. Инвестиции — что купили и сколько сейчас стоит. Доходность считается сама.
A8: 7. Баланс — наличные, вклады, недвижимость, авто (то, что у вас есть).
A9: 8. Обзор — итоги месяца, чистый капитал и прогресс к цели. Месяц меняется в ячейке B3.
A10: 9. Сводка по месяцам — таблица за год с нормой сбережений.
A11: Жёлтые ячейки — то, что нужно заполнять. Остальное считается автоматически.
A12: Ожидаемая доходность — номинальная, без гарантий. Налоги и инфляция в расчёт не входят.

Sheet Обзор
A1: Мои финансы — обзор
A3: Месяц (любая дата в нужном месяце) | B3: =DATE(YEAR(TODAY()),MONTH(TODAY()),1)
A4: Начало месяца | B4: =DATE(YEAR(B3),MONTH(B3),1)
A5: Конец месяца (не включая) | B5: =EDATE(B4,1)
A7: За месяц
A8: Доходы | B8: =SUMIFS(Операции!$D:$D,Операции!$B:$B,"Доход",Операции!$A:$A,">="&$B$4,Операции!$A:$A,"<"&$B$5)
A9: Возвраты долгов (вам вернули) | B9: =SUMIFS(Платежи!$C:$C,Платежи!$D:$D,"Мне должны",Платежи!$A:$A,">="&$B$4,Платежи!$A:$A,"<"&$B$5)
A10: Расходы | B10: =SUMIFS(Операции!$D:$D,Операции!$B:$B,"Расход",Операции!$A:$A,">="&$B$4,Операции!$A:$A,"<"&$B$5)
A11: Подписки (в месяц) | B11: =Подписки!$E$501
A12: Платежи по долгам (вы отдали) | B12: =SUMIFS(Платежи!$C:$C,Платежи!$D:$D,"Я должен",Платежи!$A:$A,">="&$B$4,Платежи!$A:$A,"<"&$B$5)
A13: Остаток за месяц | B13: =B8+B9-B10-B11-B12
A14: Норма сбережений | B14: =IF(B8+B9=0,"",B13/(B8+B9))
A16: Капитал (на сегодня)
A17: Наличные, вклады и имущество | B17: =Баланс!$C$501
A18: Инвестиции (текущая стоимость) | B18: =Инвестиции!$E$501
A19: Мне должны (остаток) | B19: =SUMIFS(Долги!$I:$I,Долги!$B:$B,"Мне должны")
A20: Я должен (остаток) | B20: =SUMIFS(Долги!$I:$I,Долги!$B:$B,"Я должен")
A21: Чистый капитал | B21: =B17+B18+B19-B20
A23: Цель
A24: Цель: инвестиционный капитал | B24: =Настройки!$B$4
A25: Инвестиции сейчас | B25: =B18
A26: Прогресс к цели | B26: =IF(B24=0,"",B25/B24)
A27: Лет до цели | B27: =Настройки!$B$6
A28: Нужно откладывать в месяц | B28: =IF(Настройки!$B$7=0,"",MAX(0,PMT(Настройки!$B$5/12,Настройки!$B$7,B25,-B24)))
A29: Сейчас откладываете (остаток за месяц) | B29: =B13
A30: Ежемесячные платежи по долгам (вы отдаёте) | B30: =SUMIFS(Долги!$F:$F,Долги!$B:$B,"Я должен",Долги!$I:$I,">0")

Sheet Настройки
A1: Настройка | B1: Значение
A2: Текущий возраст | B2: 34
A3: Целевой возраст | B3: 40
A4: Цель: инвестиционный капитал (€) | B4: 1000000
A5: Ожидаемая доходность в год (номинально) | B5: 0.07
A6: Лет до цели | B6: =MAX(0,B3-B2)
A7: Месяцев до цели | B7: =B6*12
A8: Год для сводки по месяцам (по умолчанию текущий) | B8: =YEAR(TODAY())

Sheet Операции
A1: Дата | B1: Тип | C1: Категория | D1: Сумма (€) | E1: Счёт | F1: Комментарий

Sheet Подписки
A1: Название | B1: Сумма (€) | C1: Период | D1: Включена | E1: В месяц (€) | F1: Дата след. списания | G1: Комментарий
E2: =IF(OR(A2="",D2="Нет"),0,IF(C2="в год",B2/12,B2))
E3: =IF(OR(A3="",D3="Нет"),0,IF(C3="в год",B3/12,B3))
E4: =IF(OR(A4="",D4="Нет"),0,IF(C4="в год",B4/12,B4))
E5: =IF(OR(A5="",D5="Нет"),0,IF(C5="в год",B5/12,B5))
E6: =IF(OR(A6="",D6="Нет"),0,IF(C6="в год",B6/12,B6))
E7: =IF(OR(A7="",D7="Нет"),0,IF(C7="в год",B7/12,B7))
E8: =IF(OR(A8="",D8="Нет"),0,IF(C8="в год",B8/12,B8))
E9: =IF(OR(A9="",D9="Нет"),0,IF(C9="в год",B9/12,B9))
E10: =IF(OR(A10="",D10="Нет"),0,IF(C10="в год",B10/12,B10))
E11: =IF(OR(A11="",D11="Нет"),0,IF(C11="в год",B11/12,B11))
E12: =IF(OR(A12="",D12="Нет"),0,IF(C12="в год",B12/12,B12))
E13: =IF(OR(A13="",D13="Нет"),0,IF(C13="в год",B13/12,B13))
... E500: =IF(OR(A500="",D500="Нет"),0,IF(C500="в год",B500/12,B500))
E501: =SUM(E2:E500) | G501: Итого в месяц:

Sheet Долги
A1: Название (кому / от кого) | B1: Направление | C1: Вид | D1: Исходная сумма (€) | E1: Ставка, % годовых | F1: Ежемесячный платёж (€) | G1: Дата окончания | H1: Выплачено (€) | I1: Остаток (€) | J1: Погашено, %
H2: =IF(A2="","",SUMIFS(Платежи!$C:$C,Платежи!$B:$B,A2)) | I2: =IF(A2="","",MAX(0,D2-H2)) | J2: =IF(OR(A2="",D2=0),"",H2/D2)
H3: =IF(A3="","",SUMIFS(Платежи!$C:$C,Платежи!$B:$B,A3)) | I3: =IF(A3="","",MAX(0,D3-H3)) | J3: =IF(OR(A3="",D3=0),"",H3/D3)
H4: =IF(A4="","",SUMIFS(Платежи!$C:$C,Платежи!$B:$B,A4)) | I4: =IF(A4="","",MAX(0,D4-H4)) | J4: =IF(OR(A4="",D4=0),"",H4/D4)
H5: =IF(A5="","",SUMIFS(Платежи!$C:$C,Платежи!$B:$B,A5)) | I5: =IF(A5="","",MAX(0,D5-H5)) | J5: =IF(OR(A5="",D5=0),"",H5/D5)
H6: =IF(A6="","",SUMIFS(Платежи!$C:$C,Платежи!$B:$B,A6)) | I6: =IF(A6="","",MAX(0,D6-H6)) | J6: =IF(OR(A6="",D6=0),"",H6/D6)
H7: =IF(A7="","",SUMIFS(Платежи!$C:$C,Платежи!$B:$B,A7)) | I7: =IF(A7="","",MAX(0,D7-H7)) | J7: =IF(OR(A7="",D7=0),"",H7/D7)
H8: =IF(A8="","",SUMIFS(Платежи!$C:$C,Платежи!$B:$B,A8)) | I8: =IF(A8="","",MAX(0,D8-H8)) | J8: =IF(OR(A8="",D8=0),"",H8/D8)
H9: =IF(A9="","",SUMIFS(Платежи!$C:$C,Платежи!$B:$B,A9)) | I9: =IF(A9="","",MAX(0,D9-H9)) | J9: =IF(OR(A9="",D9=0),"",H9/D9)
H10: =IF(A10="","",SUMIFS(Платежи!$C:$C,Платежи!$B:$B,A10)) | I10: =IF(A10="","",MAX(0,D10-H10)) | J10: =IF(OR(A10="",D10=0),"",H10/D10)
H11: =IF(A11="","",SUMIFS(Платежи!$C:$C,Платежи!$B:$B,A11)) | I11: =IF(A11="","",MAX(0,D11-H11)) | J11: =IF(OR(A11="",D11=0),"",H11/D11)
H12: =IF(A12="","",SUMIFS(Платежи!$C:$C,Платежи!$B:$B,A12)) | I12: =IF(A12="","",MAX(0,D12-H12)) | J12: =IF(OR(A12="",D12=0),"",H12/D12)
H13: =IF(A13="","",SUMIFS(Платежи!$C:$C,Платежи!$B:$B,A13)) | I13: =IF(A13="","",MAX(0,D13-H13)) | J13: =IF(OR(A13="",D13=0),"",H13/D13)
... H500: =IF(A500="","",SUMIFS(Платежи!$C:$C,Платежи!$B:$B,A500)) | I500: =IF(A500="","",MAX(0,D500-H500)) | J500: =IF(OR(A500="",D500=0),"",H500/D500)

Sheet Платежи
A1: Дата | B1: Долг (из списка «Долги») | C1: Сумма (€) | D1: Направление
D2: =IF(B2="","",IFERROR(VLOOKUP(B2,Долги!$A$2:$B$500,2,FALSE),""))
D3: =IF(B3="","",IFERROR(VLOOKUP(B3,Долги!$A$2:$B$500,2,FALSE),""))
D4: =IF(B4="","",IFERROR(VLOOKUP(B4,Долги!$A$2:$B$500,2,FALSE),""))
D5: =IF(B5="","",IFERROR(VLOOKUP(B5,Долги!$A$2:$B$500,2,FALSE),""))
D6: =IF(B6="","",IFERROR(VLOOKUP(B6,Долги!$A$2:$B$500,2,FALSE),""))
D7: =IF(B7="","",IFERROR(VLOOKUP(B7,Долги!$A$2:$B$500,2,FALSE),""))
D8: =IF(B8="","",IFERROR(VLOOKUP(B8,Долги!$A$2:$B$500,2,FALSE),""))
D9: =IF(B9="","",IFERROR(VLOOKUP(B9,Долги!$A$2:$B$500,2,FALSE),""))
D10: =IF(B10="","",IFERROR(VLOOKUP(B10,Долги!$A$2:$B$500,2,FALSE),""))
D11: =IF(B11="","",IFERROR(VLOOKUP(B11,Долги!$A$2:$B$500,2,FALSE),""))
D12: =IF(B12="","",IFERROR(VLOOKUP(B12,Долги!$A$2:$B$500,2,FALSE),""))
D13: =IF(B13="","",IFERROR(VLOOKUP(B13,Долги!$A$2:$B$500,2,FALSE),""))
... D500: =IF(B500="","",IFERROR(VLOOKUP(B500,Долги!$A$2:$B$500,2,FALSE),""))

Sheet Инвестиции
A1: Дата покупки | B1: Инструмент | C1: Тип | D1: Вложено (€) | E1: Текущая стоимость (€) | F1: Доходность | G1: Комментарий
F2: =IF(OR(D2="",D2=0),"",(E2-D2)/D2)
F3: =IF(OR(D3="",D3=0),"",(E3-D3)/D3)
F4: =IF(OR(D4="",D4=0),"",(E4-D4)/D4)
F5: =IF(OR(D5="",D5=0),"",(E5-D5)/D5)
F6: =IF(OR(D6="",D6=0),"",(E6-D6)/D6)
F7: =IF(OR(D7="",D7=0),"",(E7-D7)/D7)
F8: =IF(OR(D8="",D8=0),"",(E8-D8)/D8)
F9: =IF(OR(D9="",D9=0),"",(E9-D9)/D9)
F10: =IF(OR(D10="",D10=0),"",(E10-D10)/D10)
F11: =IF(OR(D11="",D11=0),"",(E11-D11)/D11)
F12: =IF(OR(D12="",D12=0),"",(E12-D12)/D12)
F13: =IF(OR(D13="",D13=0),"",(E13-D13)/D13)
... F500: =IF(OR(D500="",D500=0),"",(E500-D500)/D500)
B501: Итого: | D501: =SUM(D2:D500) | E501: =SUM(E2:E500) | F501: =IF(D501=0,"",(E501-D501)/D501)

Sheet Баланс
A1: Тип актива | B1: Название | C1: Стоимость (€) | D1: Дата обновления
B501: Итого активов: | C501: =SUM(C2:C500)

Sheet Сводка по месяцам
A1: Месяц | B1: Доходы (€) | C1: Возвраты долгов (€) | D1: Расходы (€) | E1: Подписки (€) | F1: Платежи по долгам (€) | G1: Остаток (€) | H1: Норма сбережений
A2: =DATE(Настройки!$B$8,1,1) | B2: =SUMIFS(Операции!$D:$D,Операции!$B:$B,"Доход",Операции!$A:$A,">="&$A2,Операции!$A:$A,"<"&EDATE($A2,1)) | C2: =SUMIFS(Платежи!$C:$C,Платежи!$D:$D,"Мне должны",Платежи!$A:$A,">="&$A2,Платежи!$A:$A,"<"&EDATE($A2,1)) | D2: =SUMIFS(Операции!$D:$D,Операции!$B:$B,"Расход",Операции!$A:$A,">="&$A2,Операции!$A:$A,"<"&EDATE($A2,1)) | E2: =Подписки!$E$501 | F2: =SUMIFS(Платежи!$C:$C,Платежи!$D:$D,"Я должен",Платежи!$A:$A,">="&$A2,Платежи!$A:$A,"<"&EDATE($A2,1)) | G2: =B2+C2-D2-E2-F2 | H2: =IF(B2+C2=0,"",G2/(B2+C2))
A3: =EDATE(A2,1) | B3: =SUMIFS(Операции!$D:$D,Операции!$B:$B,"Доход",Операции!$A:$A,">="&$A3,Операции!$A:$A,"<"&EDATE($A3,1)) | C3: =SUMIFS(Платежи!$C:$C,Платежи!$D:$D,"Мне должны",Платежи!$A:$A,">="&$A3,Платежи!$A:$A,"<"&EDATE($A3,1)) | D3: =SUMIFS(Операции!$D:$D,Операции!$B:$B,"Расход",Операции!$A:$A,">="&$A3,Операции!$A:$A,"<"&EDATE($A3,1)) | E3: =Подписки!$E$501 | F3: =SUMIFS(Платежи!$C:$C,Платежи!$D:$D,"Я должен",Платежи!$A:$A,">="&$A3,Платежи!$A:$A,"<"&EDATE($A3,1)) | G3: =B3+C3-D3-E3-F3 | H3: =IF(B3+C3=0,"",G3/(B3+C3))
A4: =EDATE(A3,1) | B4: =SUMIFS(Операции!$D:$D,Операции!$B:$B,"Доход",Операции!$A:$A,">="&$A4,Операции!$A:$A,"<"&EDATE($A4,1)) | C4: =SUMIFS(Платежи!$C:$C,Платежи!$D:$D,"Мне должны",Платежи!$A:$A,">="&$A4,Платежи!$A:$A,"<"&EDATE($A4,1)) | D4: =SUMIFS(Операции!$D:$D,Операции!$B:$B,"Расход",Операции!$A:$A,">="&$A4,Операции!$A:$A,"<"&EDATE($A4,1)) | E4: =Подписки!$E$501 | F4: =SUMIFS(Платежи!$C:$C,Платежи!$D:$D,"Я должен",Платежи!$A:$A,">="&$A4,Платежи!$A:$A,"<"&EDATE($A4,1)) | G4: =B4+C4-D4-E4-F4 | H4: =IF(B4+C4=0,"",G4/(B4+C4))
A5: =EDATE(A4,1) | B5: =SUMIFS(Операции!$D:$D,Операции!$B:$B,"Доход",Операции!$A:$A,">="&$A5,Операции!$A:$A,"<"&EDATE($A5,1)) | C5: =SUMIFS(Платежи!$C:$C,Платежи!$D:$D,"Мне должны",Платежи!$A:$A,">="&$A5,Платежи!$A:$A,"<"&EDATE($A5,1)) | D5: =SUMIFS(Операции!$D:$D,Операции!$B:$B,"Расход",Операции!$A:$A,">="&$A5,Операции!$A:$A,"<"&EDATE($A5,1)) | E5: =Подписки!$E$501 | F5: =SUMIFS(Платежи!$C:$C,Платежи!$D:$D,"Я должен",Платежи!$A:$A,">="&$A5,Платежи!$A:$A,"<"&EDATE($A5,1)) | G5: =B5+C5-D5-E5-F5 | H5: =IF(B5+C5=0,"",G5/(B5+C5))
A6: =EDATE(A5,1) | B6: =SUMIFS(Операции!$D:$D,Операции!$B:$B,"Доход",Операции!$A:$A,">="&$A6,Операции!$A:$A,"<"&EDATE($A6,1)) | C6: =SUMIFS(Платежи!$C:$C,Платежи!$D:$D,"Мне должны",Платежи!$A:$A,">="&$A6,Платежи!$A:$A,"<"&EDATE($A6,1)) | D6: =SUMIFS(Операции!$D:$D,Операции!$B:$B,"Расход",Операции!$A:$A,">="&$A6,Операции!$A:$A,"<"&EDATE($A6,1)) | E6: =Подписки!$E$501 | F6: =SUMIFS(Платежи!$C:$C,Платежи!$D:$D,"Я должен",Платежи!$A:$A,">="&$A6,Платежи!$A:$A,"<"&EDATE($A6,1)) | G6: =B6+C6-D6-E6-F6 | H6: =IF(B6+C6=0,"",G6/(B6+C6))
A7: =EDATE(A6,1) | B7: =SUMIFS(Операции!$D:$D,Операции!$B:$B,"Доход",Операции!$A:$A,">="&$A7,Операции!$A:$A,"<"&EDATE($A7,1)) | C7: =SUMIFS(Платежи!$C:$C,Платежи!$D:$D,"Мне должны",Платежи!$A:$A,">="&$A7,Платежи!$A:$A,"<"&EDATE($A7,1)) | D7: =SUMIFS(Операции!$D:$D,Операции!$B:$B,"Расход",Операции!$A:$A,">="&$A7,Операции!$A:$A,"<"&EDATE($A7,1)) | E7: =Подписки!$E$501 | F7: =SUMIFS(Платежи!$C:$C,Платежи!$D:$D,"Я должен",Платежи!$A:$A,">="&$A7,Платежи!$A:$A,"<"&EDATE($A7,1)) | G7: =B7+C7-D7-E7-F7 | H7: =IF(B7+C7=0,"",G7/(B7+C7))
A8: =EDATE(A7,1) | B8: =SUMIFS(Операции!$D:$D,Операции!$B:$B,"Доход",Операции!$A:$A,">="&$A8,Операции!$A:$A,"<"&EDATE($A8,1)) | C8: =SUMIFS(Платежи!$C:$C,Платежи!$D:$D,"Мне должны",Платежи!$A:$A,">="&$A8,Платежи!$A:$A,"<"&EDATE($A8,1)) | D8: =SUMIFS(Операции!$D:$D,Операции!$B:$B,"Расход",Операции!$A:$A,">="&$A8,Операции!$A:$A,"<"&EDATE($A8,1)) | E8: =Подписки!$E$501 | F8: =SUMIFS(Платежи!$C:$C,Платежи!$D:$D,"Я должен",Платежи!$A:$A,">="&$A8,Платежи!$A:$A,"<"&EDATE($A8,1)) | G8: =B8+C8-D8-E8-F8 | H8: =IF(B8+C8=0,"",G8/(B8+C8))
A9: =EDATE(A8,1) | B9: =SUMIFS(Операции!$D:$D,Операции!$B:$B,"Доход",Операции!$A:$A,">="&$A9,Операции!$A:$A,"<"&EDATE($A9,1)) | C9: =SUMIFS(Платежи!$C:$C,Платежи!$D:$D,"Мне должны",Платежи!$A:$A,">="&$A9,Платежи!$A:$A,"<"&EDATE($A9,1)) | D9: =SUMIFS(Операции!$D:$D,Операции!$B:$B,"Расход",Операции!$A:$A,">="&$A9,Операции!$A:$A,"<"&EDATE($A9,1)) | E9: =Подписки!$E$501 | F9: =SUMIFS(Платежи!$C:$C,Платежи!$D:$D,"Я должен",Платежи!$A:$A,">="&$A9,Платежи!$A:$A,"<"&EDATE($A9,1)) | G9: =B9+C9-D9-E9-F9 | H9: =IF(B9+C9=0,"",G9/(B9+C9))
A10: =EDATE(A9,1) | B10: =SUMIFS(Операции!$D:$D,Операции!$B:$B,"Доход",Операции!$A:$A,">="&$A10,Операции!$A:$A,"<"&EDATE($A10,1)) | C10: =SUMIFS(Платежи!$C:$C,Платежи!$D:$D,"Мне должны",Платежи!$A:$A,">="&$A10,Платежи!$A:$A,"<"&EDATE($A10,1)) | D10: =SUMIFS(Операции!$D:$D,Операции!$B:$B,"Расход",Операции!$A:$A,">="&$A10,Операции!$A:$A,"<"&EDATE($A10,1)) | E10: =Подписки!$E$501 | F10: =SUMIFS(Платежи!$C:$C,Платежи!$D:$D,"Я должен",Платежи!$A:$A,">="&$A10,Платежи!$A:$A,"<"&EDATE($A10,1)) | G10: =B10+C10-D10-E10-F10 | H10: =IF(B10+C10=0,"",G10/(B10+C10))
A11: =EDATE(A10,1) | B11: =SUMIFS(Операции!$D:$D,Операции!$B:$B,"Доход",Операции!$A:$A,">="&$A11,Операции!$A:$A,"<"&EDATE($A11,1)) | C11: =SUMIFS(Платежи!$C:$C,Платежи!$D:$D,"Мне должны",Платежи!$A:$A,">="&$A11,Платежи!$A:$A,"<"&EDATE($A11,1)) | D11: =SUMIFS(Операции!$D:$D,Операции!$B:$B,"Расход",Операции!$A:$A,">="&$A11,Операции!$A:$A,"<"&EDATE($A11,1)) | E11: =Подписки!$E$501 | F11: =SUMIFS(Платежи!$C:$C,Платежи!$D:$D,"Я должен",Платежи!$A:$A,">="&$A11,Платежи!$A:$A,"<"&EDATE($A11,1)) | G11: =B11+C11-D11-E11-F11 | H11: =IF(B11+C11=0,"",G11/(B11+C11))
A12: =EDATE(A11,1) | B12: =SUMIFS(Операции!$D:$D,Операции!$B:$B,"Доход",Операции!$A:$A,">="&$A12,Операции!$A:$A,"<"&EDATE($A12,1)) | C12: =SUMIFS(Платежи!$C:$C,Платежи!$D:$D,"Мне должны",Платежи!$A:$A,">="&$A12,Платежи!$A:$A,"<"&EDATE($A12,1)) | D12: =SUMIFS(Операции!$D:$D,Операции!$B:$B,"Расход",Операции!$A:$A,">="&$A12,Операции!$A:$A,"<"&EDATE($A12,1)) | E12: =Подписки!$E$501 | F12: =SUMIFS(Платежи!$C:$C,Платежи!$D:$D,"Я должен",Платежи!$A:$A,">="&$A12,Платежи!$A:$A,"<"&EDATE($A12,1)) | G12: =B12+C12-D12-E12-F12 | H12: =IF(B12+C12=0,"",G12/(B12+C12))
A13: =EDATE(A12,1) | B13: =SUMIFS(Операции!$D:$D,Операции!$B:$B,"Доход",Операции!$A:$A,">="&$A13,Операции!$A:$A,"<"&EDATE($A13,1)) | C13: =SUMIFS(Платежи!$C:$C,Платежи!$D:$D,"Мне должны",Платежи!$A:$A,">="&$A13,Платежи!$A:$A,"<"&EDATE($A13,1)) | D13: =SUMIFS(Операции!$D:$D,Операции!$B:$B,"Расход",Операции!$A:$A,">="&$A13,Операции!$A:$A,"<"&EDATE($A13,1)) | E13: =Подписки!$E$501 | F13: =SUMIFS(Платежи!$C:$C,Платежи!$D:$D,"Я должен",Платежи!$A:$A,">="&$A13,Платежи!$A:$A,"<"&EDATE($A13,1)) | G13: =B13+C13-D13-E13-F13 | H13: =IF(B13+C13=0,"",G13/(B13+C13))
A14: Итого за 12 месяцев | B14: =SUM(B2:B13) | C14: =SUM(C2:C13) | D14: =SUM(D2:D13) | E14: =SUM(E2:E13) | F14: =SUM(F2:F13) | G14: =SUM(G2:G13)

Sheet Списки
A1: Категории | B1: Тип операции | C1: Направление долга | D1: Вид долга | E1: Период подписки | F1: Включена | G1: Тип инвестиции | H1: Тип актива
A2: Зарплата | B2: Доход | C2: Я должен | D2: Кредит | E2: в месяц | F2: Да | G2: Фонды | H2: Наличные
A3: Доход от фирмы | B3: Расход | C3: Мне должны | D3: Ипотека | E3: в год | F3: Нет | G3: Акции | H3: Вклад / счёт
A4: Дивиденды | D4: Займ | G4: Облигации | H4: Недвижимость
A5: Проценты | D5: Кредитная карта | G5: Вклад | H5: Авто
A6: Подарки | D6: Лизинг | G6: Крипто | H6: Прочее
A7: Прочий доход | D7: Рассрочка | G7: Другое
A8: Продукты | D8: Частный долг
A9: Рестораны | D9: Другое
A10: Транспорт
A11: Жильё
A12: Коммунальные
A13: Связь
A14: Здоровье
A15: Одежда
A16: Развлечения
A17: Образование
A18: Путешествия
A19: Прочие расходы
